CHANGES.rst
LICENSE.txt
MANIFEST.in
README.rst
setup.py
exr/__init__.py
exr/meta_aws.py
exr/aws/__init__.py
exr/aws/_common.py
exr/aws/shared.py
exr/aws/services/__init__.py
exr/aws/services/_cloudformation.py
exr/aws/services/_cloudfront.py
exr/aws/services/_ec2.py
exr/aws/services/_iam.py
exr/aws/services/_lambda.py
exr/aws/services/_logs.py
exr/aws/services/_s3.py
exr/aws/services/_session.py
exr_aws.egg-info/PKG-INFO
exr_aws.egg-info/SOURCES.txt
exr_aws.egg-info/dependency_links.txt
exr_aws.egg-info/requires.txt
exr_aws.egg-info/top_level.txt