Metadata-Version: 1.1
Name: exr-aws
Version: 0.1.6
Summary: Amazon AWS boto3 helper libs.
Home-page: https://code.exrny.com/opensource/exr-aws/
Author: Peter Salnikov
Author-email: opensource@exrny.com
License: MIT License
Keywords: framework
Platform: UNKNOWN
Classifier: Development Status :: 4 - Beta
Classifier: Environment :: Console
Classifier: Intended Audience :: System Administrators
Classifier: Intended Audience :: Developers
Classifier: License :: OSI Approved :: MIT License
Classifier: Programming Language :: Python :: 2
Classifier: Programming Language :: Python :: 3
